moreprot/MoReProt.py
moreprot/__init__.py
moreprot-1.0.2.dist-info/METADATA
moreprot-1.0.2.dist-info/WHEEL
moreprot-1.0.2.dist-info/top_level.txt
moreprot-1.0.2.dist-info/RECORD
